README.md
setup.py
BayesClassifiers/__init__.py
BayesClassifiers.egg-info/PKG-INFO
BayesClassifiers.egg-info/SOURCES.txt
BayesClassifiers.egg-info/dependency_links.txt
BayesClassifiers.egg-info/not-zip-safe
BayesClassifiers.egg-info/top_level.txt