Metadata-Version: 1.0
Name: BayesClassifiers
Version: 0.3
Summary: NaiveBayes | BayesClassifier | SemiparametricBayesClassifier
Home-page: https://github.com/HladkyiIvan/BayesClassifiers
Author: Hladkyi Ivan
Author-email: liberte1793@gmail.com
License: MIT
Platform: UNKNOWN
